xw_utils.cpython-39-i386-linux-gnu.so
xw_utils.libs/libgcc_s-8b50eaaa.so.1
xw_utils.libs/libstdc++-8baf04f9.so.6.0.28
xw_utils-1.2.2.dist-info/WHEEL
xw_utils-1.2.2.dist-info/RECORD
xw_utils-1.2.2.dist-info/LICENSE
xw_utils-1.2.2.dist-info/METADATA
xw_utils-1.2.2.dist-info/top_level.txt
